{
  "id": 74431740,
  "name": "Assault Reboot",
  "is_illegal": false,
  "is_custom": false,
  "text": "Tribute 1 \"/Assault Mode\" monster; Special Summon 1 \"/Assault Mode\" monster from your Deck with a different name in Defense Position, ignoring its Summoning conditions. You can banish this card from your GY, then target any number of cards in your GY, with different names, that are \"Assault Mode Activate\" and/or specifically list \"Assault Mode Activate\" in their text, except \"Assault Reboot\"; shuffle them into the Deck. You can only use each effect of \"Assault Reboot\" once per turn.",
  "images": [
    "https://storage.googleapis.com/ygoprodeck.com/pics/74431740.jpg"
  ],
  "type": "Trap",
  "trap_type": "Normal"
}