{
  "id": 60681103,
  "name": "Divine Dragon Lord Felgrand",
  "is_illegal": false,
  "text": "If this card is Special Summoned from the Graveyard: You can target 1 monster your opponent controls or in their Graveyard; banish it, and if you do, this card gains ATK and DEF equal to the banished monster\u0027s original Level/Rank x 100. If this card destroys an opponent\u0027s monster by battle: You can target 1 Level 7 or 8 Dragon-Type monster in the Graveyard, except \"Divine Dragon Lord Felgrand\"; Special Summon it to your field.",
  "images": [
    "https://storage.googleapis.com/ygoprodeck.com/pics/60681103.jpg"
  ],
  "type": "Monster",
  "attribute": "LIGHT",
  "atk": 2800,
  "species": "Dragon",
  "monster_type": "",
  "is_pendulum": false,
  "ability": "",
  "has_effect": true,
  "def": 2800,
  "level": 8,
  "is_tuner": false
}