{
  "id": 3429238,
  "name": "Drill Warrior",
  "is_illegal": false,
  "text": "\"Drill Synchron\" + 1 or more non-Tuner monsters\nOnce per turn, during your Main Phase 1: You can halve this card\u0027s ATK, and if you do, it can attack your opponent directly this turn. Once per turn: You can discard 1 card, and if you do, banish this card. During your next Standby Phase: Special Summon this card banished by this effect, then add 1 monster from your Graveyard to your hand.",
  "type": "Monster",
  "attribute": "EARTH",
  "atk": 2400,
  "species": "Warrior",
  "monster_type": "Synchro",
  "is_pendulum": false,
  "ability": "",
  "has_effect": true,
  "def": 2000,
  "level": 6,
  "is_tuner": false
}