{
  "id": 94784213,
  "name": "Majespecter Fox - Kyubi",
  "is_illegal": false,
  "text": "When this card is Normal or Special Summoned: You can add 1 \"Majespecter\" Trap Card from your Deck to your hand. You can only use this effect of \"Majespecter Fox - Kyubi\" once per turn. Cannot be targeted or destroyed by your opponent\u0027s card effects.",
  "images": [
    "https://storage.googleapis.com/ygoprodeck.com/pics/94784213.jpg"
  ],
  "type": "Monster",
  "attribute": "WIND",
  "atk": 1500,
  "species": "Spellcaster",
  "monster_type": "",
  "is_pendulum": true,
  "ability": "",
  "has_effect": true,
  "def": 1000,
  "level": 4,
  "is_tuner": false,
  "pendulum_text": "",
  "pendulum_scale_left_blue": 2,
  "pendulum_scale_right_red": 2
}