{
  "id": 11845050,
  "name": "Right-Hand Shark",
  "is_illegal": false,
  "text": "When this card is Normal Summoned: You can add 1 \"Left-Hand Shark\" from your Deck to your hand. If this card is in your GY and you control no monsters: You can Special Summon this card, but banish it when it leaves the field. An Xyz Monster that was Summoned using only WATER monsters, including this card on the field, as material gains this effect.\n? Cannot be destroyed by battle.\nYou can only use each effect of \"Right-Hand Shark\" once per turn.",
  "images": [
    "https://storage.googleapis.com/ygoprodeck.com/pics/11845050.jpg"
  ],
  "type": "Monster",
  "attribute": "WATER",
  "atk": 1500,
  "species": "Fish",
  "monster_type": "",
  "is_pendulum": false,
  "ability": "",
  "has_effect": true,
  "def": 1300,
  "level": 4,
  "is_tuner": false
}