{
  "id": 84976088,
  "name": "Background Dragon",
  "is_illegal": false,
  "is_custom": false,
  "text": "If this card is in the GY and you control no cards: You can Special Summon both this card, and 1 Level 4 or lower Dragon monster from your hand, in Defense Position, but banish this card when it leaves the field. You can only use this effect of \"Background Dragon\" once per turn.",
  "images": [
    "https://images.ygoprodeck.com/images/cards/84976088.jpg"
  ],
  "type": "Monster",
  "attribute": "DARK",
  "atk": 1600,
  "species": "Dragon",
  "monster_type": "",
  "is_pendulum": false,
  "ability": "",
  "has_effect": true,
  "def": 1800,
  "level": 5,
  "is_tuner": false
}