{
  "id": 47198668,
  "name": "D/D/D Doom King Armageddon",
  "illegal": false,
  "custom": false,
  "text": "Once per turn, if a monster(s) you control is destroyed by battle or card effect: You can target 1 of those monsters; this card gains ATK equal to that monster\u0027s original ATK until the end of this turn. This card cannot attack your opponent directly during the turn this effect is activated. Cannot be destroyed by Spell/Trap effects that do not target this card.",
  "images": [
    "https://storage.googleapis.com/ygoprodeck.com/pics/47198668.jpg"
  ],
  "type": "Monster",
  "attribute": "DARK",
  "atk": 3000,
  "species": "Fiend",
  "monster_type": "",
  "is_pendulum": true,
  "ability": "",
  "has_effect": true,
  "def": 1000,
  "level": 8,
  "is_tuner": false,
  "pendulum_text": "Once per turn: You can target 1 \"D/D\" monster you control; it gains 800 ATK until the end of this turn (even if this card leaves the field).\n",
  "pendulum_scale_left_blue": 4,
  "pendulum_scale_right_red": 4
}