{
  "id": 53408006,
  "name": "Gem-Merchant",
  "is_illegal": false,
  "is_custom": false,
  "text": "During the Damage Step, in either player\u0027s turn, when a face-up EARTH Normal Monster you control attacks or is attacked: You can send this card from your hand to the Graveyard; that monster gains 1000 ATK and DEF until the End Phase.",
  "images": [
    "https://storage.googleapis.com/ygoprodeck.com/pics/53408006.jpg"
  ],
  "type": "Monster",
  "attribute": "EARTH",
  "atk": 1000,
  "species": "Spellcaster",
  "monster_type": "",
  "is_pendulum": false,
  "ability": "",
  "has_effect": true,
  "def": 1000,
  "level": 3,
  "is_tuner": false
}