{
  "id": 61639289,
  "name": "Igknight Crusader",
  "is_illegal": false,
  "text": "This impulsive Igknight warrior is fanatical about the causes he fights for. Because of this passion, his comrades try to keep him at arm\u0027s length.",
  "images": [
    "https://storage.googleapis.com/ygoprodeck.com/pics/61639289.jpg"
  ],
  "type": "Monster",
  "attribute": "FIRE",
  "atk": 1600,
  "species": "Warrior",
  "monster_type": "",
  "is_pendulum": true,
  "ability": "",
  "has_effect": false,
  "def": 300,
  "level": 3,
  "is_tuner": false,
  "pendulum_text": "If you have an \"Igknight\" card in your other Pendulum Zone: You can destroy both cards in your Pendulum Zones, and if you do, add 1 FIRE Warrior-Type monster from your Deck or Graveyard to your hand.\n",
  "pendulum_scale_left_blue": 2,
  "pendulum_scale_right_red": 2
}