{
  "id": 80032567,
  "name": "Jurrac Giganoto",
  "is_illegal": false,
  "is_custom": false,
  "text": "1 Tuner + 1 or more non-Tuner Dinosaur-Type monsters\nAll face-up \"Jurrac\" monsters you control gain 200 ATK for each \"Jurrac\" monster in your Graveyard.",
  "images": [
    "https://images.ygoprodeck.com/images/cards/80032567.jpg"
  ],
  "type": "Monster",
  "attribute": "FIRE",
  "atk": 2100,
  "species": "Dinosaur",
  "monster_type": "Synchro",
  "is_pendulum": false,
  "ability": "",
  "has_effect": true,
  "def": 1800,
  "level": 7,
  "is_tuner": false
}