{
  "id": 45796834,
  "name": "Maha Vailo of Apramanabha",
  "is_illegal": false,
  "is_custom": false,
  "text": "This card gains these effects based on the number of Equip Cards equipped to it.\n? 1+: Gains 1000 ATK for each Equip Card equipped to it.\n? 2+: Your opponent cannot activate monster effects during the Battle Phase.\n? 3+: When your opponent activates a card or effect that targets this card (Quick Effect): You can send 1 Equip Card you control to the GY; negate that effect.\n? 4+: Your opponent cannot activate card effects during the Battle Phase.\n? 5+: Any battle damage this card inflicts to your opponent is doubled.",
  "images": [
    "https://storage.googleapis.com/ygoprodeck.com/pics/45796834.jpg"
  ],
  "type": "Monster",
  "attribute": "LIGHT",
  "atk": 1550,
  "species": "Spellcaster",
  "monster_type": "",
  "is_pendulum": false,
  "ability": "",
  "has_effect": true,
  "def": 1400,
  "level": 8,
  "is_tuner": false
}