{
  "id": 16226786,
  "name": "Night Assailant",
  "is_illegal": false,
  "is_custom": false,
  "text": "FLIP: Target 1 monster your opponent controls; destroy that target.\nWhen this card is sent from the hand to the Graveyard: Target 1 Flip Effect Monster in your Graveyard, except this card; return that target to the hand.",
  "images": [
    "https://storage.googleapis.com/ygoprodeck.com/pics/16226786.jpg"
  ],
  "type": "Monster",
  "attribute": "DARK",
  "atk": 200,
  "species": "Fiend",
  "monster_type": "",
  "is_pendulum": false,
  "ability": "Flip",
  "has_effect": true,
  "def": 500,
  "level": 3,
  "is_tuner": false
}