{
  "id": 35037880,
  "name": "Saber Reflection",
  "illegal": false,
  "custom": false,
  "text": "When you take battle or effect damage while you control an \"X-Saber\" monster: Gain LP equal to the damage you took, and if you do, inflict the same amount of damage to your opponent, then you can add 1 \"Saber\" Spell/Trap Card or \"Gottoms\" card from your Deck to your hand. You can only activate 1 \"Saber Reflection\" per turn.",
  "images": [
    "https://storage.googleapis.com/ygoprodeck.com/pics/35037880.jpg"
  ],
  "type": "Spell",
  "spell_type": "Quick-Play"
}