{
  "id": 83135907,
  "name": "Scrap Goblin",
  "is_illegal": false,
  "is_custom": false,
  "text": "This card cannot be destroyed by battle. If this face-up Defense Position card is selected as an attack target, destroy this card at the end of the Battle Phase. If this card is destroyed by the effect of a \"Scrap\" card and sent to the Graveyard, you can select 1 \"Scrap\" monster in your Graveyard, except \"Scrap Goblin\", and add it to your hand.",
  "images": [
    "https://storage.googleapis.com/ygoprodeck.com/pics/83135907.jpg"
  ],
  "type": "Monster",
  "attribute": "EARTH",
  "atk": 0,
  "species": "Beast-Warrior",
  "monster_type": "",
  "is_pendulum": false,
  "ability": "",
  "has_effect": true,
  "def": 500,
  "level": 3,
  "is_tuner": true
}