{
  "id": 44335251,
  "name": "Souleating Oviraptor",
  "is_illegal": false,
  "is_custom": false,
  "text": "If this card is Normal or Special Summoned: You can take 1 Dinosaur-Type monster from your Deck, and either add it to your hand or send it to the Graveyard. You can target 1 other Level 4 or lower Dinosaur-Type monster on the field; destroy it, then Special Summon 1 Dinosaur-Type monster from your Graveyard in Defense Position. You can only use each effect of \"Souleating Oviraptor\" once per turn.",
  "images": [
    "https://images.ygoprodeck.com/images/cards/44335251.jpg"
  ],
  "type": "Monster",
  "attribute": "DARK",
  "atk": 1800,
  "species": "Dinosaur",
  "monster_type": "",
  "is_pendulum": false,
  "ability": "",
  "has_effect": true,
  "def": 500,
  "level": 4,
  "is_tuner": false
}