{
  "id": 15381421,
  "name": "Starliege Seyfert",
  "is_illegal": false,
  "text": "You can send any number of Dragon monsters from your hand and/or face-up field to the GY; add 1 Dragon monster from your Deck to your hand, whose Level equals the total original Levels of those monsters sent to the GY. You can banish this card from your GY, then target 1 Level 8 LIGHT or DARK Dragon monster in your GY; add it to your hand. You can only use each effect of \"Starliege Seyfert\" once per turn.",
  "images": [
    "https://storage.googleapis.com/ygoprodeck.com/pics/15381421.jpg"
  ],
  "type": "Monster",
  "attribute": "LIGHT",
  "atk": 1800,
  "species": "Dragon",
  "monster_type": "",
  "is_pendulum": false,
  "ability": "",
  "has_effect": true,
  "def": 0,
  "level": 4,
  "is_tuner": false
}