{
  "id": 49514333,
  "name": "Tiki Soul",
  "is_illegal": false,
  "is_custom": false,
  "text": "Special Summon this card as an Effect Monster (Rock-Type/LIGHT/Level 4/ATK 1000/DEF 1800). (This card is also still a Trap Card.) While this card is an Effect Monster, if another Trap Card you control that is a monster would be destroyed by your opponent\u0027s card (either by battle or by card effect) and sent to your Graveyard, you can Set it in the Spell \u0026 Trap Card Zone instead.",
  "images": [
    "https://storage.googleapis.com/ygoprodeck.com/pics/49514333.jpg"
  ],
  "type": "Trap",
  "trap_type": "Continuous"
}