{
  "id": 52331012,
  "name": "Tribrigade Lugerou the Silver Bullet",
  "is_illegal": false,
  "is_custom": false,
  "text": "2+ Beast, Beast-Warrior, and/or Winged Beast monsters\n During your opponent\u0027s Main Phase (Quick Effect): You can Special Summon 1 Level 4 or lower Beast, Beast-Warrior, or Winged Beast monster from your hand or GY, but negate its effects, also return it to the hand during the End Phase. If this card is sent to the GY: You can make all monsters your opponent currently controls lose 300 ATK for each monster you control with a different Type, until the end of this turn. You can only use each effect of \"Tribrigade Lugerou the Silver Bullet\" once per turn.",
  "images": [
    "https://storage.googleapis.com/ygoprodeck.com/pics/52331012.jpg"
  ],
  "type": "Monster",
  "attribute": "EARTH",
  "atk": 2300,
  "species": "Beast-Warrior",
  "monster_type": "Link",
  "is_pendulum": false,
  "ability": "",
  "has_effect": true,
  "link_rating": 1,
  "link_arrows": 56
}