{
  "id": 47459126,
  "name": "Tuned Magician",
  "is_illegal": false,
  "is_custom": false,
  "text": "This card is treated as a Normal Monster while face-up on the field or in the Graveyard. While this card is face-up on the field, you can Normal Summon it to have it be treated as an Effect Monster with this effect:\n? This card is treated as a Tuner monster.",
  "images": [
    "https://images.ygoprodeck.com/images/cards/47459126.jpg"
  ],
  "type": "Monster",
  "attribute": "WIND",
  "atk": 1800,
  "species": "Spellcaster",
  "monster_type": "",
  "is_pendulum": false,
  "ability": "Gemini",
  "has_effect": true,
  "def": 1600,
  "level": 4,
  "is_tuner": false
}